drekar_launch_process.py
drekar_launch_process-0.1.3.dist-info/LICENSE.txt
drekar_launch_process-0.1.3.dist-info/METADATA
drekar_launch_process-0.1.3.dist-info/WHEEL
drekar_launch_process-0.1.3.dist-info/top_level.txt
drekar_launch_process-0.1.3.dist-info/RECORD
