Metadata-Version: 2.1
Name: drekar-launch-process
Version: 0.1.3
Summary: Client library for drekar-launch
Author-email: John Wason <wason@wasontech.com>
License: Apache-2.0
Requires-Python: >=3.6
License-File: LICENSE.txt
Provides-Extra: test
Requires-Dist: pytest ; extra == 'test'
Requires-Dist: pywin32 ; (platform_system == "Windows") and extra == 'test'
